setup.cfg
setup.py
instapy_testers2/__init__.py
instapy_testers2/browser.py
instapy_testers2/clarifai_util.py
instapy_testers2/comment_util.py
instapy_testers2/commenters_util.py
instapy_testers2/constants.py
instapy_testers2/database_engine.py
instapy_testers2/event.py
instapy_testers2/exceptions.py
instapy_testers2/feed_util.py
instapy_testers2/file_manager.py
instapy_testers2/follow_util.py
instapy_testers2/instapy.py
instapy_testers2/like_util.py
instapy_testers2/login_util.py
instapy_testers2/monkey_patcher.py
instapy_testers2/pods_util.py
instapy_testers2/print_log_writer.py
instapy_testers2/quota_supervisor.py
instapy_testers2/relationship_tools.py
instapy_testers2/settings.py
instapy_testers2/story_util.py
instapy_testers2/text_analytics.py
instapy_testers2/time_util.py
instapy_testers2/unfollow_util.py
instapy_testers2/util.py
instapy_testers2/xpath.py
instapy_testers2/xpath_compile.py
instapy_testers2.egg-info/PKG-INFO
instapy_testers2.egg-info/SOURCES.txt
instapy_testers2.egg-info/dependency_links.txt
instapy_testers2.egg-info/not-zip-safe
instapy_testers2.egg-info/top_level.txt