Metadata-Version: 2.1
Name: instapy-testers2
Version: 1.0
Summary: Instapy corrected module for the best usefull
Home-page: UNKNOWN
Author-email: lokasan@inbox.ru
License: UNKNOWN
Platform: UNKNOWN
